MANIFEST.in
setup.cfg
setup.py
Panacea.egg-info/PKG-INFO
Panacea.egg-info/SOURCES.txt
Panacea.egg-info/dependency_links.txt
Panacea.egg-info/requires.txt
Panacea.egg-info/top_level.txt
panacea/__init__.py
panacea/collection.py
panacea/entity.py
panacea/events.py
panacea/fields.py
panacea/options.py
panacea/properties.py
panacea/relationships.py
panacea/statements.py
panacea/ext/__init__.py
panacea/ext/associable.py
panacea/ext/encrypted.py
panacea/ext/perform_ddl.py
panacea/ext/versioned.py
tests/db1/__init__.py
tests/db1/a.py
tests/db1/b.py
tests/db1/c.py
tests/db2/__init__.py
tests/db2/a.py