Metadata-Version: 1.0
Name: Panacea
Version: 0.8.0
Summary: Declarative Mapper for SQLAlchemy (Forked from Elixir)
Home-page: https://github.com/jmg/Panacea/
Author: Juan Manuel Garcia
Author-email: jmg.utn@gmail.com
License: MIT License
Platform: UNKNOWN
Classifier: Development Status :: 5 - Production/Stable
Classifier: Intended Audience :: Developers
Classifier: License :: OSI Approved :: MIT License
Classifier: Operating System :: OS Independent
Classifier: Programming Language :: Python
Classifier: Topic :: Database :: Front-Ends
Classifier: Topic :: Software Development :: Libraries :: Python Modules
